invenio_edugain/__init__.py
invenio_edugain-0.0.1.dist-info/METADATA
invenio_edugain-0.0.1.dist-info/WHEEL
invenio_edugain-0.0.1.dist-info/licenses/LICENSE
invenio_edugain-0.0.1.dist-info/RECORD
