Metadata-Version: 2.4
Name: invenio-edugain
Version: 0.0.1
Summary: Invenio extension for login via edugain.
Project-URL: Repository, https://github.com/tu-graz-library/invenio-edugain
Author-email: Graz University of Technology <info@tugraz.at>
License: MIT License
License-File: LICENSE
Keywords: edugain,invenio
Classifier: Development Status :: 4 - Beta
Classifier: License :: OSI Approved :: MIT License
Classifier: Operating System :: OS Independent
Classifier: Programming Language :: Python
Classifier: Topic :: Software Development :: Libraries :: Python Modules
Requires-Python: >=3.9
Provides-Extra: tests
Requires-Dist: pytest-black>=0.6.0; extra == 'tests'
Requires-Dist: pytest-invenio>=3.0.0; extra == 'tests'
Requires-Dist: ruff>=0.9.6; extra == 'tests'
